vintasend_fastapi_mail/__init__.py
vintasend_fastapi_mail/py.typed
vintasend_fastapi_mail/services/__init__.py
vintasend_fastapi_mail/services/notification_adapters/__init__.py
vintasend_fastapi_mail/services/notification_adapters/fastapi_mail.py
vintasend_fastapi_mail/services/tests/__init__.py
vintasend_fastapi_mail/services/tests/test_adapters.py
vintasend_fastapi_mail-0.1.4.dist-info/LICENSE.txt
vintasend_fastapi_mail-0.1.4.dist-info/METADATA
vintasend_fastapi_mail-0.1.4.dist-info/WHEEL
vintasend_fastapi_mail-0.1.4.dist-info/RECORD
